{
    "last_sync": "09-07-2026",
    "what-im-building": {
        "title": "Stremio South Indian Add-on"
    },
    "current_sprint": [
        {
            "title": "Extend Picking Flow for Multi Pick-Area Support",
            "status": "In Progress",
            "progress": 30
        }
    ],
    "deployment_env": [
        {
            "title": "FastAPI Webhook Shield",
            "status": "Deployed",
            "progress": 100
        }
    ],
    "github_metrics": {
        "recent_projects": [
            {
                "name": "portfolio-site",
                "description": "My Supply chain and Logistics inspired portfolio site showcasing my Stats, Career, and Projects.",
                "status": "Deployed"
            },
            {
                "name": "pivotlink-browser-router",
                "description": "Ever had a browser open already and Windows opened a Discord/Slack link in your default browser by launching it from scratch? Now it won't.",
                "status": "Active Development"
            }
        ],
        "commit_velocity": "High",
        "active_repositories": 32,
        "total_commits": 378,
        "top_language": "TypeScript",
        "stars_count": 68
    }
}